pastebin.py
pastebin_cli-0.1.0.dist-info/LICENSE
pastebin_cli-0.1.0.dist-info/METADATA
pastebin_cli-0.1.0.dist-info/WHEEL
pastebin_cli-0.1.0.dist-info/entry_points.txt
pastebin_cli-0.1.0.dist-info/top_level.txt
pastebin_cli-0.1.0.dist-info/RECORD
