Metadata-Version: 2.1
Name: pastebin-cli
Version: 0.1.0
Summary: Command-line interface for pastebin.com API
Home-page: https://github.com/turicas/pastebin-cli
Author: Álvaro Justen
Author-email: alvarojusten@gmail.com
License: UNKNOWN
Platform: UNKNOWN
Classifier: Programming Language :: Python :: 3
Requires-Python: >=3.5
